pyhiv/__init__.py
pyhiv/cli.py
pyhiv/config.py
pyhiv/align/__init__.py
pyhiv/align/align_with_reference.py
pyhiv/align/famsa.py
pyhiv/loading/__init__.py
pyhiv/loading/read_fastas.py
pyhiv/loading/reference_genomes/HIV1_REF_2023_genome_DNA.csv
pyhiv/loading/reference_genomes/HXB2_coordinates.csv
pyhiv/loading/reference_genomes/sequences_with_locations.tsv
pyhiv/loading/reference_genomes/HXB2_fasta/K03455-B.fasta
pyhiv/loading/reference_genomes/reference_fastas/AB253421-A1.fasta
pyhiv/loading/reference_genomes/reference_fastas/AB253429-A1.fasta
pyhiv/loading/reference_genomes/reference_fastas/AB286851-06_cpx.fasta
pyhiv/loading/reference_genomes/reference_fastas/AB485636-02_AG.fasta
pyhiv/loading/reference_genomes/reference_fastas/AB547464-33_01B.fasta
pyhiv/loading/reference_genomes/reference_fastas/AB845344-69_01B.fasta
pyhiv/loading/reference_genomes/reference_fastas/AB845347-69_01B.fasta
pyhiv/loading/reference_genomes/reference_fastas/AB845349-69_01B.fasta
pyhiv/loading/reference_genomes/reference_fastas/AF005494-F1.fasta
pyhiv/loading/reference_genomes/reference_fastas/AF005496-H.fasta
pyhiv/loading/reference_genomes/reference_fastas/AF049337-04_cpx.fasta
pyhiv/loading/reference_genomes/reference_fastas/AF061641-G.fasta
pyhiv/loading/reference_genomes/reference_fastas/AF064699-06_cpx.fasta
pyhiv/loading/reference_genomes/reference_fastas/AF067155-C.fasta
pyhiv/loading/reference_genomes/reference_fastas/AF075703-F1.fasta
pyhiv/loading/reference_genomes/reference_fastas/AF076998-05_DF.fasta
pyhiv/loading/reference_genomes/reference_fastas/AF077336-F1.fasta
pyhiv/loading/reference_genomes/reference_fastas/AF082394-J.fasta
pyhiv/loading/reference_genomes/reference_fastas/AF119819-04_cpx.fasta
pyhiv/loading/reference_genomes/reference_fastas/AF119820-04_cpx.fasta
pyhiv/loading/reference_genomes/reference_fastas/AF190127-H.fasta
pyhiv/loading/reference_genomes/reference_fastas/AF190128-H.fasta
pyhiv/loading/reference_genomes/reference_fastas/AF193253-05_DF.fasta
pyhiv_tools-0.1.0.dist-info/METADATA
pyhiv_tools-0.1.0.dist-info/WHEEL
pyhiv_tools-0.1.0.dist-info/entry_points.txt
pyhiv_tools-0.1.0.dist-info/top_level.txt
pyhiv_tools-0.1.0.dist-info/RECORD
