Metadata-Version: 2.4
Name: pyhiv-tools
Version: 0.1.0
Summary: PyHIV: A Python Package for Local HIV‑1 Sequence Alignment, Subtyping and Gene Splitting
Author: Ana Santos-Pereira
License: MIT
Keywords: HIV,SequenceAlignment,HIV-Subtyping,Bioinformatics
Platform: unix
Platform: linux
Platform: osx
Platform: cygwin
Platform: win32
Classifier: Development Status :: 3 - Alpha
Classifier: Intended Audience :: Science/Research
Classifier: License :: OSI Approved :: MIT License
Classifier: Operating System :: OS Independent
Classifier: Operating System :: Microsoft :: Windows
Classifier: Operating System :: POSIX :: Linux
Classifier: Operating System :: MacOS :: MacOS X
Classifier: Programming Language :: Python :: 3
Classifier: Programming Language :: Python :: 3 :: Only
Classifier: Programming Language :: Python :: 3.10
Classifier: Programming Language :: Python :: 3.11
Classifier: Programming Language :: Python :: 3.12
Classifier: Topic :: Scientific/Engineering :: Bio-Informatics
Requires-Python: >=3.10
Requires-Dist: pandas==2.2.3
Requires-Dist: biopython==1.85
Requires-Dist: pyfamsa==0.5.3
Requires-Dist: click>=8.0
Requires-Dist: matplotlib>=3.5.0
